__init__.py
sinapsis_data_visualization/__init__.py
sinapsis_data_visualization/helpers/__init__.py
sinapsis_data_visualization/helpers/annotation_drawer_tools.py
sinapsis_data_visualization/helpers/annotation_drawer_types.py
sinapsis_data_visualization/helpers/color_utils.py
sinapsis_data_visualization/helpers/detection_utils.py
sinapsis_data_visualization/helpers/plot_distributions.py
sinapsis_data_visualization/helpers/scikit_pca_analysis.py
sinapsis_data_visualization/helpers/tags.py
sinapsis_data_visualization/templates/__init__.py
sinapsis_data_visualization/templates/base_annotation_drawer.py
sinapsis_data_visualization/templates/base_visualization_template.py
sinapsis_data_visualization/templates/bbox_drawer.py
sinapsis_data_visualization/templates/data_distribution_visualization.py
sinapsis_data_visualization/templates/key_points_drawer.py
sinapsis_data_visualization/templates/label_drawer.py
sinapsis_data_visualization/templates/oriented_bbox_drawer.py
sinapsis_data_visualization/templates/segmentation_mask_drawer.py
sinapsis_data_visualization/templates/tabular_data_visualization.py
sinapsis_data_visualization-0.1.13.dist-info/licenses/LICENSE
sinapsis_data_visualization-0.1.13.dist-info/METADATA
sinapsis_data_visualization-0.1.13.dist-info/WHEEL
sinapsis_data_visualization-0.1.13.dist-info/top_level.txt
sinapsis_data_visualization-0.1.13.dist-info/RECORD
