Metadata-Version: 2.4
Name: sinapsis-data-visualization
Version: 0.1.13
Summary: Templates to perform visualization of data distributions and image annotations.
Author-email: SinapsisAI <dev@sinapsis.tech>
Project-URL: Homepage, https://sinapsis.tech
Project-URL: Documentation, https://docs.sinapsis.tech/docs
Project-URL: Tutorials, https://docs.sinapsis.tech/tutorials
Project-URL: Repository, https://github.com/Sinapsis-AI/sinapsis-data-tools.git
Requires-Python: >=3.10
License-File: LICENSE
Requires-Dist: numpy==1.26.4
Requires-Dist: pandas>=2.2.3
Requires-Dist: sinapsis>=0.1.1
Provides-Extra: visualization-matplotlib
Requires-Dist: matplotlib>=3.9.2; extra == "visualization-matplotlib"
Provides-Extra: all
Requires-Dist: sinapsis-data-visualization[visualization-matplotlib]; extra == "all"
Dynamic: license-file
